hooman/__init__.py
hooman/__main__.py
hooman/charts.py
hooman/check.py
hooman/colors.py
hooman/formula.py
hooman/hooman.py
hooman/result.py
hooman/shapes.py
hooman/svg.py
hooman/time.py
hooman/ui.py
hooman/widget.py
hooman-0.12.1.dist-info/LICENSE
hooman-0.12.1.dist-info/METADATA
hooman-0.12.1.dist-info/WHEEL
hooman-0.12.1.dist-info/entry_points.txt
hooman-0.12.1.dist-info/top_level.txt
hooman-0.12.1.dist-info/RECORD
