Metadata-Version: 2.1
Name: hooman
Version: 0.12.1
Summary: Pygame for humans
Home-page: https://github.com/Abdur-RahmaanJ/hooman
Author: Abdur-Rahmaan Janhangeer
Author-email: arj.python@gmail.com
Project-URL: Bug Reports, https://github.com/Abdur-RahmaanJ/hooman/issues
Project-URL: Source, https://github.com/Abdur-RahmaanJ/hooman/
Keywords: human pygame canvas api wrapper game processing
Classifier: Development Status :: 3 - Alpha
Classifier: Intended Audience :: Developers
Classifier: License :: OSI Approved :: MIT License
Classifier: Programming Language :: Python :: 3.4
Classifier: Programming Language :: Python :: 3.5
Classifier: Programming Language :: Python :: 3.6
Classifier: Programming Language :: Python :: 3.7
Classifier: Programming Language :: Python :: 3.8
Classifier: Programming Language :: Python :: 3.9
Classifier: Programming Language :: Python :: 3.10
Classifier: Programming Language :: Python :: 3.11
Classifier: Programming Language :: Python :: 3.12
Classifier: Programming Language :: Python :: 3.13
Requires-Python: >=3.4
License-File: LICENSE
Requires-Dist: numpy
